flet_charts/__init__.py
flet_charts/bar_chart.py
flet_charts/bar_chart_group.py
flet_charts/bar_chart_rod.py
flet_charts/bar_chart_rod_stack_item.py
flet_charts/candlestick_chart.py
flet_charts/candlestick_chart_spot.py
flet_charts/chart_axis.py
flet_charts/line_chart.py
flet_charts/line_chart_data.py
flet_charts/line_chart_data_point.py
flet_charts/matplotlib_chart.py
flet_charts/matplotlib_chart_with_toolbar.py
flet_charts/pie_chart.py
flet_charts/pie_chart_section.py
flet_charts/plotly_chart.py
flet_charts/radar_chart.py
flet_charts/radar_data_set.py
flet_charts/scatter_chart.py
flet_charts/scatter_chart_spot.py
flet_charts/types.py
flet_charts/matplotlib_backends/backend_flet_agg.py
flet_charts-0.80.5.dist-info/licenses/LICENSE
flutter/flet_charts/CHANGELOG.md
flutter/flet_charts/LICENSE
flutter/flet_charts/analysis_options.yaml
flutter/flet_charts/pubspec.lock
flutter/flet_charts/pubspec.yaml
flutter/flet_charts/lib/flet_charts.dart
flutter/flet_charts/lib/src/bar_chart.dart
flutter/flet_charts/lib/src/candlestick_chart.dart
flutter/flet_charts/lib/src/extension.dart
flutter/flet_charts/lib/src/line_chart.dart
flutter/flet_charts/lib/src/pie_chart.dart
flutter/flet_charts/lib/src/radar_chart.dart
flutter/flet_charts/lib/src/scatter_chart.dart
flutter/flet_charts/lib/src/utils/bar_chart.dart
flutter/flet_charts/lib/src/utils/candlestick_chart.dart
flutter/flet_charts/lib/src/utils/charts.dart
flutter/flet_charts/lib/src/utils/line_chart.dart
flutter/flet_charts/lib/src/utils/pie_chart.dart
flutter/flet_charts/lib/src/utils/radar_chart.dart
flutter/flet_charts/lib/src/utils/scatter_chart.dart
flet_charts-0.80.5.dist-info/METADATA
flet_charts-0.80.5.dist-info/WHEEL
flet_charts-0.80.5.dist-info/top_level.txt
flet_charts-0.80.5.dist-info/RECORD
